auth_app/__init__.py
auth_app/admin.py
auth_app/api_views.py
auth_app/apps.py
auth_app/forms.py
auth_app/models.py
auth_app/serializers.py
auth_app/tests.py
auth_app/urls.py
auth_app/views.py
auth_app/migrations/0001_initial.py
auth_app/migrations/__init__.py
auth_app/templates/auth_app/base.html
auth_app/templates/auth_app/home.html
auth_app/templates/auth_app/login.html
auth_app/templates/auth_app/otp_verify.html
auth_app/templates/auth_app/password_change.html
auth_app/templates/auth_app/password_reset.html
auth_app/templates/auth_app/password_reset_confirm.html
auth_app/templates/auth_app/register_admin.html
auth_app/templates/auth_app/register_customer.html
django_auth_app-0.3.2.dist-info/METADATA
django_auth_app-0.3.2.dist-info/WHEEL
django_auth_app-0.3.2.dist-info/top_level.txt
django_auth_app-0.3.2.dist-info/RECORD
