Metadata-Version: 2.1
Name: django-auth-app
Version: 0.3.2
Summary: A Django authentication boilerplate with OTP and role-based access control
Home-page: https://github.com/sajan69/django-auth-boilerplate
Author: Sajan Adhikari
Author-email: sajana46@gmail.com
License: MIT
Classifier: Development Status :: 3 - Alpha
Classifier: Framework :: Django
Classifier: Intended Audience :: Developers
Classifier: License :: OSI Approved :: MIT License
Classifier: Programming Language :: Python :: 3
Classifier: Programming Language :: Python :: 3.8
Classifier: Programming Language :: Python :: 3.9
Requires-Python: >=3.8
Requires-Dist: django>=3.0
Requires-Dist: djangorestframework
Requires-Dist: drf-yasg
Requires-Dist: setuptools
Requires-Dist: PyJWT
Requires-Dist: requests
